compute_line.cpython-38-darwin.so
autostereogram/__init__.py
autostereogram/compute_line.pyx
autostereogram/converter.py
autostereogram/sirds_converter.py
autostereogram/noise/__init__.py
autostereogram/noise/colored.py
autostereogram/noise/perlin2d.py
pystereogram-0.0.20.dist-info/LICENSE
pystereogram-0.0.20.dist-info/METADATA
pystereogram-0.0.20.dist-info/WHEEL
pystereogram-0.0.20.dist-info/top_level.txt
pystereogram-0.0.20.dist-info/RECORD
