Metadata-Version: 2.1
Name: pystereogram
Version: 0.0.20
Summary: A library supporting efficient stereogram image computation.
Home-page: https://github.com/yxiao1996/pystereogram
Author: Yu Xiao
License: UNKNOWN
Platform: UNKNOWN
License-File: LICENSE
Requires-Dist: numpy (>=1.19.2)
